[
  {
    "res": "금정회관 학생 식당",
    "date": "2024-11-11",
    "day": "월요일",
    "meals": [
      {
        "when": "조식",
        "mealType": "천원아침",
        "menu": "기장밥\n<br>콩나물유부장국\n<br>돈가스/소스\n<br>비엔나햄볶음\n<br>모밀야채무침\n<br>배추김치\n<br>"
      },
      {
        "when": "조식",
        "mealType": "정식-4,000원",
        "menu": "기장밥\n<br>콩나물유부장국\n<br>돈가스/소스\n<br>비엔나햄볶음\n<br>모밀야채무침\n<br>배추김치\n<br>"
      },
      {
        "when": "중식",
        "mealType": "정식-4,000원",
        "menu": "흑미밥\n<br>사골떡국\n<br>깐풍기/소스\n<br>잡채어묵조림\n<br>오이소박이\n<br>배추김치\n<br>"
      },
      {
        "when": "중식",
        "mealType": "정식-4,000원",
        "menu": "기장밥\n<br>쇠고기미역국\n<br>순살치킨/매콤간장\n<br>하이라이스\n<br>오이무침\n<br>배추김치\n<br>"
      },
      {
        "when": "석식",
        "mealType": "정식-4,000원",
        "menu": "흑미밥\n<br>육개장\n<br>닭고구마간장조림\n<br>떡볶이\n<br>콩나물맛살무침\n<br>배추김치\n<br>"
      },
      {
        "when": "석식",
        "mealType": "일품1-4,000원",
        "menu": "새우튀김우동\n<br>돈육김치주먹밥\n<br>배추김치\n<br>"
      }
    ]
  },
  {
    "res": "금정회관 학생 식당",
    "date": "2024-11-12",
    "day": "화요일",
    "meals": [
      {
        "when": "조식",
        "mealType": "천원아침",
        "menu": "백미밥\n<br>감자수제비국\n<br>찜닭\n<br>소시지전+케찹\n<br>두부톳무침\n<br>배추김치\n<br>"
      },
      {
        "when": "조식",
        "mealType": "정식-4,000원",
        "menu": "백미밥\n<br>감자수제비국\n<br>찜닭\n<br>소시지전+케찹\n<br>두부톳무침\n<br>배추김치\n<br>"
      },
      {
        "when": "중식",
        "mealType": "일품1-4,000원",
        "menu": "불고기갈릭버섯볶음밥\n<br>된장국\n<br>스파게티/소스\n<br>야채샐러드/드레싱\n<br>배추김치\n<br>"
      },
      {
        "when": "중식",
        "mealType": "정식-4,000원",
        "menu": "백미밥\n<br>만두국\n<br>돈육김치찜\n<br>동그랑땡데리야끼조림\n<br>청경채겉절이\n<br>배추김치\n<br>"
      },
      {
        "when": "석식",
        "mealType": "정식-4,000원",
        "menu": "백미밥\n<br>닭개장\n<br>꿔바로우/소스\n<br>매콤우동볶음\n<br>부추겉절이\n<br>배추김치\n<br>"
      },
      {
        "when": "석식",
        "mealType": "일품1-4,000원",
        "menu": "닭갈비덮밥(김가루)\n<br>된장국\n<br>해쉬브라운/케찹\n<br>배추김치\n<br>"
      }
    ]
  },
  {
    "res": "금정회관 학생 식당",
    "date": "2024-11-13",
    "day": "수요일",
    "meals": [
      {
        "when": "조식",
        "mealType": "천원아침",
        "menu": "백미밥\n<br>닭곰탕(사리)\n<br>탕수육/소스\n<br>순대볶음\n<br>부추겉절이\n<br>배추김치\n<br>"
      },
      {
        "when": "조식",
        "mealType": "정식-4,000원",
        "menu": "백미밥\n<br>닭곰탕(사리)\n<br>탕수육/소스\n<br>순대볶음\n<br>부추겉절이\n<br>배추김치\n<br>"
      },
      {
        "when": "중식",
        "mealType": "일품1-4,000원",
        "menu": "비빔밥(후라이)\n<br>고기볶음/표고/미역줄기\n<br>콩나물/무생채\n<br>미역장국\n<br>배추김치\n<br>요구르트\n<br>"
      },
      {
        "when": "중식",
        "mealType": "정식-4,000원",
        "menu": "현미밥\n<br>어묵국\n<br>닭갈비\n<br>만두탕수/소스\n<br>숙주나물무침\n<br>배추김치\n<br>"
      },
      {
        "when": "석식",
        "mealType": "정식-4,000원",
        "menu": "백미밥\n<br>바지락버섯된장국\n<br>도톰떡갈비/데리야끼\n<br>마파두부\n<br>콩나물무침\n<br>배추김치\n<br>"
      },
      {
        "when": "석식",
        "mealType": "일품1-4,000원",
        "menu": "자장면+후라이\n<br>맑은국\n<br>단무지/김치\n<br>망고주스\n<br>"
      }
    ]
  },
  {
    "res": "금정회관 학생 식당",
    "date": "2024-11-14",
    "day": "목요일",
    "meals": [
      {
        "when": "조식",
        "mealType": "천원아침",
        "menu": "백미밥\n<br>모듬햄김치국(사리)\n<br>치킨가스/소스\n<br>감자조림\n<br>열무겉절이\n<br>배추김치\n<br>"
      },
      {
        "when": "조식",
        "mealType": "정식-4,000원",
        "menu": "백미밥\n<br>모듬햄김치국(사리)\n<br>치킨가스/소스\n<br>감자조림\n<br>열무겉절이\n<br>배추김치\n<br>"
      },
      {
        "when": "중식",
        "mealType": "일품1-4,000원",
        "menu": "백미밥\n<br>고구마돈가스\n<br>옥수수콘프레이크스프\n<br>야채샐러드/드레싱\n<br>배추김치\n<br>"
      },
      {
        "when": "중식",
        "mealType": "정식-4,000원",
        "menu": "백미밥\n<br>시금치유부장국\n<br>돈육불고기\n<br>두부조림\n<br>부추겉절이\n<br>배추김치\n<br>"
      },
      {
        "when": "석식",
        "mealType": "정식-4,000원",
        "menu": "백미밥\n<br>오징어보탕국\n<br>볼카츠/소스\n<br>계란찜\n<br>사각어묵무침\n<br>배추김치\n<br>"
      },
      {
        "when": "석식",
        "mealType": "일품1-4,000원",
        "menu": "돈육큐브바베규덮밥\n<br>(스크럼블/깻잎)\n<br>된장국\n<br>쫄면야채무침\n<br>배추김치\n<br>"
      }
    ]
  },
  {
    "res": "금정회관 학생 식당",
    "date": "2024-11-15",
    "day": "금요일",
    "meals": [
      {
        "when": "조식",
        "mealType": "천원아침",
        "menu": "흑미밥\n<br>사골떡국\n<br>깐풍기/소스\n<br>잡채어묵조림\n<br>오이소박이\n<br>배추김치\n<br>"
      },
      {
        "when": "조식",
        "mealType": "정식-4,000원",
        "menu": "흑미밥\n<br>사골떡국\n<br>깐풍기/소스\n<br>잡채어묵조림\n<br>오이소박이\n<br>배추김치\n<br>"
      },
      {
        "when": "중식",
        "mealType": "일품1-4,000원",
        "menu": "백미밥\n<br>돼지국밥(사리)\n<br>생선가스/소스\n<br>부추겉절이\n<br>깍두기\n<br>요구르트\n<br>"
      },
      {
        "when": "중식",
        "mealType": "정식-4,000원",
        "menu": "흑미밥\n<br>육개장\n<br>닭고구마간장조림\n<br>떡볶이\n<br>콩나물맛살무침\n<br>배추김치\n<br>"
      },
      {
        "when": "석식",
        "mealType": "정식-4,000원",
        "menu": "백미밥\n<br>꽃게탕\n<br>통살새우가스/칠리\n<br>버섯잡채\n<br>참치김치볶음\n<br>깍두기\n<br>"
      },
      {
        "when": "석식",
        "mealType": "일품1-4,000원",
        "menu": "삼겹살김치볶음밥\n<br>후라이/된장국\n<br>야채샐러드/드레싱\n<br>배추김치\n<br>요구르트\n<br>"
      }
    ]
  },
  {
    "res": "금정회관 학생 식당",
    "date": "2024-11-16",
    "day": "토요일",
    "meals": [
      {
        "when": "조식",
        "mealType": "정식-4,000원",
        "menu": "기장밥\n<br>쇠고기미역국\n<br>순살치킨/매콤간장\n<br>하이라이스\n<br>오이무침\n<br>배추김치\n<br>"
      },
      {
        "when": "조식",
        "mealType": "일품1-4,000원",
        "menu": "불고기갈릭버섯볶음밥\n<br>된장국\n<br>스파게티/소스\n<br>야채샐러드/드레싱\n<br>배추김치\n<br>"
      },
      {
        "when": "중식",
        "mealType": "일품1-4,000원",
        "menu": "새우튀김우동\n<br>돈육김치주먹밥\n<br>배추김치\n<br>"
      },
      {
        "when": "중식",
        "mealType": "정식-4,000원",
        "menu": "백미밥\n<br>닭개장\n<br>꿔바로우/소스\n<br>매콤우동볶음\n<br>부추겉절이\n<br>배추김치\n<br>"
      },
      {
        "when": "석식",
        "mealType": "정식-4,000원",
        "menu": "백미밥\n<br>바지락콩나물국\n<br>도톰함박+소스\n<br>비엔나햄볶음\n<br>소면야채무침\n<br>배추김치\n<br>"
      },
      {
        "when": "석식",
        "mealType": "일품1-4,000원",
        "menu": "백미밥(후리카케)\n<br>치킨치즈/해쉬브라운+케찹\n<br>파슬리스프\n<br>야채샐러드/드레싱\n<br>배추김치\n<br>"
      }
    ]
  }
]